MANIFEST.in
setup.py
finny/__init__.py
finny/command.py
finny/exceptions.py
finny/runner.py
finny.egg-info/PKG-INFO
finny.egg-info/SOURCES.txt
finny.egg-info/dependency_links.txt
finny.egg-info/entry_points.txt
finny.egg-info/requires.txt
finny.egg-info/top_level.txt
finny/boot/__init__.py
finny/boot/boot_helper.py
finny/commands/__init__.py
finny/commands/generate_endpoint.py
finny/commands/generate_runner.py
finny/commands/generate_structure.py
finny/commands/templates/.gitignore.jinja
finny/commands/templates/README.md.jinja
finny/commands/templates/__init__.py.jinja
finny/commands/templates/manage.py.jinja
finny/commands/templates/requirements.txt.jinja
finny/commands/templates/config/boot.py.jinja
finny/commands/templates/config/development.py.sample.jinja
finny/commands/templates/config/production.py.sample.jinja
finny/commands/templates/config/test.py.sample.jinja
finny/commands/templates/endpoint/api.py.jinja
finny/commands/templates/endpoint/model.py.jinja
finny/commands/templates/initializers/app.py.jinja
finny/commands/templates/runners/default.py.jinja
finny/env/__init__.py
finny/tests/__init__.py
finny/tests/load_fixture.py
finny/tests/resource_test.py
finny/views/__init__.py
finny/views/fixtures.py
finny/views/restful_view.py